src/__init__.py
src/server.py
orange_mcp_server_ccxt-0.1.0.dist-info/METADATA
orange_mcp_server_ccxt-0.1.0.dist-info/WHEEL
orange_mcp_server_ccxt-0.1.0.dist-info/entry_points.txt
orange_mcp_server_ccxt-0.1.0.dist-info/licenses/LICENSE
orange_mcp_server_ccxt-0.1.0.dist-info/RECORD
